django_messages_display/__init__.py
django_messages_display/static/django_messages_display/django_messages_display.css
django_messages_display/templates/django_messages_display/close_button.html
django_messages_display/templates/django_messages_display/django_messages_display.html
django_messages_display/templatetags/__init__.py
django_messages_display/templatetags/django_messages_display.py
django_messages_display-0.5.0.dist-info/LICENCE
django_messages_display-0.5.0.dist-info/METADATA
django_messages_display-0.5.0.dist-info/WHEEL
django_messages_display-0.5.0.dist-info/top_level.txt
django_messages_display-0.5.0.dist-info/RECORD
